logPPP/__init__.py
logPPP-1.3.0.dist-info/METADATA
logPPP-1.3.0.dist-info/WHEEL
logPPP-1.3.0.dist-info/top_level.txt
logPPP-1.3.0.dist-info/RECORD
