Metadata-Version: 2.1
Name: logPPP
Version: 1.3.0
Summary: logPPP
Home-page: https://github.com/Aurorax-own/logPPP
Author: Aurorax-own
Author-email: 15047150695@163.com
Project-URL: Source, https://github.com/Aurorax-own/logPPP
Project-URL: Tracker, https://github.com/Aurorax-own/logPPP/issues
